blastutils.py
blastutils-1.0.1.dist-info/METADATA
blastutils-1.0.1.dist-info/WHEEL
blastutils-1.0.1.dist-info/top_level.txt
blastutils-1.0.1.dist-info/RECORD
