Metadata-Version: 2.1
Name: blastutils
Version: 1.0.1
Summary: BLAST Utilities
Home-page: https://github.com/lawley0316/blastutils
Author: Lawley
Author-email: lawley0316@gmail.com
License: MIT
Classifier: License :: OSI Approved :: MIT License
Classifier: Programming Language :: Python
Classifier: Programming Language :: Python :: 3
Classifier: Programming Language :: Python :: 3.6
Classifier: Programming Language :: Python :: Implementation :: CPython
Classifier: Programming Language :: Python :: Implementation :: PyPy
Requires-Python: >=3.6.0
